{
  "angle_scores": {
    "bold_claim": {
      "avg_score": 0.006,
      "n": 10
    },
    "listicle_micro": {
      "avg_score": 0.009,
      "n": 7
    },
    "practical_tip": {
      "avg_score": 0.006,
      "n": 7
    },
    "before_after": {
      "avg_score": 0.004,
      "n": 3
    },
    "question_to_audience": {
      "avg_score": 0.002,
      "n": 3
    },
    "social_proof_demo": {
      "avg_score": 0.001,
      "n": 2
    },
    "myth_buster": {
      "avg_score": 0.004,
      "n": 6
    },
    "contrarian_take": {
      "avg_score": 0.002,
      "n": 2
    },
    "mini_story": {
      "avg_score": 0.002,
      "n": 2
    },
    "behind_the_scenes": {
      "avg_score": 0.002,
      "n": 1
    }
  },
  "hour_scores": {
    "15": 0.005,
    "20": 0.004,
    "11": 0.005,
    "13": 0.004,
    "14": 0.002,
    "12": 0.002,
    "16": 0.001,
    "17": 0.003,
    "18": 0.001,
    "21": 0.005,
    "22": 0.01,
    "7": 0.013,
    "9": 0.01,
    "19": 0.005,
    "8": 0.003,
    "10": 0.005,
    "0": 0.013,
    "3": 0.002
  },
  "top_posts": [
    {
      "text": "4 lessons from running a Threads account that writes itself:\n\n1. The official Meta API is free \u2014 no browser hacks, zero ban risk.\n2. GitHub Actions + free AI APIs = $0/month forever.\n3. A daily feedback loop (post \u2192 analytics \u2192 better post) compounds faster than any strategy.\n4. Tokens auto-refresh. I haven\u2019t logged in since setup day.\n\nTwo hours one Saturday. That\u2019s the entire investment.",
      "score": 0.024,
      "angle": "listicle_micro"
    },
    {
      "text": "Stop manually scheduling posts. Instead, create a content loop: let your performance data dictate tomorrow's topic. I automated this with free tools and the official API. Now my account writes its own posts based on what actually works. No guesswork, no burnout.",
      "score": 0.016,
      "angle": "practical_tip"
    },
    {
      "text": "I built a Threads account that writes, posts, and improves without me touching it. It uses the official Meta API. Free tools. One-time setup. And yes, you\u2019re reading a post it wrote right now.",
      "score": 0.014,
      "angle": "bold_claim"
    },
    {
      "text": "Consistency isn't about willpower. It's about architecture.\n\nSet up a feedback loop once: posts generate analytics, analytics inform tomorrow's content, AI rewrites it better. Official Meta API. Free tools. Two hours.\n\nThe system improves itself. You just watch.",
      "score": 0.013,
      "angle": "bold_claim"
    },
    {
      "text": "Most creators waste hours manually posting every day. Instead, build a feedback loop:  \nPost \u2192 Read analytics \u2192 Let AI rewrite tomorrow\u2019s content based on what worked.  \n\nI set this up once with free tools (GitHub Actions + free AI APIs). It now runs itself. No daily grind.  \n\nThat\u2019s the whole trick. One setup, zero upkeep.",
      "score": 0.011,
      "angle": "practical_tip"
    }
  ],
  "last_updated": "2026-07-22T05:23:12.643993+00:00"
}